MANIFEST.in
README.md
setup.py
brlcad/__init__.py
brlcad.egg-info/PKG-INFO
brlcad.egg-info/SOURCES.txt
brlcad.egg-info/dependency_links.txt
brlcad.egg-info/not-zip-safe
brlcad.egg-info/requires.txt
brlcad.egg-info/top_level.txt
brlcad/install/__init__.py
brlcad/install/post_install.py