Metadata-Version: 1.0
Name: brlcad
Version: 0.0.1
Summary: An attempt at a post-install script.
Home-page: https://github.com/kanzure/python-brlcad
Author: Bryan Bishop
Author-email: kanzure@gmail.com
License: UNKNOWN
Platform: UNKNOWN
